WaterAPI/__init__.py
WaterAPI/main.py
WaterLib-0.1.0rc1.dist-info/LICENSE
WaterLib-0.1.0rc1.dist-info/METADATA
WaterLib-0.1.0rc1.dist-info/WHEEL
WaterLib-0.1.0rc1.dist-info/top_level.txt
WaterLib-0.1.0rc1.dist-info/RECORD
